README.md
setup.py
pyaasp/__init__.py
pyaasp.egg-info/PKG-INFO
pyaasp.egg-info/SOURCES.txt
pyaasp.egg-info/dependency_links.txt
pyaasp.egg-info/not-zip-safe
pyaasp.egg-info/requires.txt
pyaasp.egg-info/top_level.txt
pyaasp/dl/__init__.py
pyaasp/ortho/__init__.py
pyaasp/ortho/divne.py
pyaasp/ortho/drr3d.py
pyaasp/ortho/localortho.py
pyaasp/ortho/localsimi.py
pyaasp/ortho/snr.py
pyaasp/seistr/__init__.py